{
  "Lable": "桌子1女",
  "Transform": {
    "Pos": {
      "X": 5038.134051720225,
      "Y": -5305.593042359339,
      "Z": 188.00005700002015
    },
    "Rot": {
      "Z": 89.99999999297219
    }
  },
  "PrefabId": 1006,
  "Guid": "E658D4EC4176DC553DE779858E4319C5",
  "ComponentsState": {
    "FlowComponent": {
      "InitState": {
        "FlowListName": "流程_村民",
        "FlowId": 10,
        "StateId": 1
      }
    },
    "BehaviorFlowComponent": {
      "InitStateId": 0,
      "FlowInfo": {
        "Id": 0,
        "Name": "Empty",
        "StateGenId": 1,
        "States": [
          {
            "Id": 0,
            "Name": "状态1",
            "Actions": []
          }
        ]
      },
      "Disabled": true
    },
    "MoveComponent": {
      "InitSpeed": 150,
      "Disabled": true
    },
    "NpcComponent": {
      "Content": "",
      "Icon": "",
      "Disabled": false
    }
  }
}